ml_dronebase_data_utils/__init__.py
ml_dronebase_data_utils/bbox/__init__.py
ml_dronebase_data_utils/bbox/box_mode.py
ml_dronebase_data_utils/bbox/box_utils.py
ml_dronebase_data_utils/bbox/visualize.py
ml_dronebase_data_utils/geo/__init__.py
ml_dronebase_data_utils/geo/convert_geojson.py
ml_dronebase_data_utils/geo/convert_geojson_cli.py
ml_dronebase_data_utils/geo/geo_utils.py
ml_dronebase_data_utils/geo/visualize_converted_geojson.py
ml_dronebase_data_utils/s3/__init__.py
ml_dronebase_data_utils/s3/s3.py
ml_dronebase_data_utils/voc/__init__.py
ml_dronebase_data_utils/voc/parse_voc.py
ml_dronebase_data_utils/voc/pascal_voc.py
ml_dronebase_data_utils/voc/templates/annotation.xml
ml_dronebase_data_utils-0.4.0.dist-info/METADATA
ml_dronebase_data_utils-0.4.0.dist-info/WHEEL
ml_dronebase_data_utils-0.4.0.dist-info/entry_points.txt
ml_dronebase_data_utils-0.4.0.dist-info/top_level.txt
ml_dronebase_data_utils-0.4.0.dist-info/RECORD
