Metadata-Version: 2.1
Name: ml-dronebase-data-utils
Version: 0.4.0
Summary: A collection of commonly functions used by DroneBase ML Engineers
Home-page: https://github.com/DroneBase/ml-dronebase-data-utils
Author: Sourav Agrawal, Isaac Corley, Jonathan Lwowski, Conor Wallace
Author-email: sourav.agrawal@zeitview.com, isaac.corley@zeitview.com, jonathan.lwowski@zeitview.com, conor.wallace@zeitview.com
Keywords: python,utilities
Classifier: Development Status :: 5 - Production/Stable
Classifier: Intended Audience :: Science/Research
Classifier: Programming Language :: Python :: 3.9
Classifier: Programming Language :: Python :: 3.10
Classifier: Operating System :: OS Independent
Requires-Python: <3.11,>=3.9
Requires-Dist: tqdm <5.0.0
Provides-Extra: all
Requires-Dist: ml-dronebase-data-utils[bbox,dev,geo,s3,voc] ; extra == 'all'
Provides-Extra: bbox
Requires-Dist: Pillow <11.0.0 ; extra == 'bbox'
Requires-Dist: Shapely <3.0.0 ; extra == 'bbox'
Requires-Dist: torch <3.0.0 ; extra == 'bbox'
Provides-Extra: dev
Requires-Dist: black ; extra == 'dev'
Requires-Dist: flake8 ; extra == 'dev'
Requires-Dist: flake8-bugbear ; extra == 'dev'
Requires-Dist: isort[colors] ; extra == 'dev'
Requires-Dist: pytest ; extra == 'dev'
Requires-Dist: pytest-cov ; extra == 'dev'
Requires-Dist: Pillow <11.0.0 ; extra == 'dev'
Requires-Dist: numpy <2.0.0 ; extra == 'dev'
Provides-Extra: geo
Requires-Dist: ml-dronebase-data-utils[bbox,s3,voc] ; extra == 'geo'
Requires-Dist: numpy <2.0.0 ; extra == 'geo'
Requires-Dist: geopandas <1.0.0 ; extra == 'geo'
Requires-Dist: rasterio <2.0.0 ; extra == 'geo'
Provides-Extra: s3
Requires-Dist: boto3 <2.0.0 ; extra == 's3'
Requires-Dist: scikit-learn <2.0.0 ; extra == 's3'
Provides-Extra: voc
Requires-Dist: ml-dronebase-data-utils[bbox] ; extra == 'voc'
Requires-Dist: jinja2 <4.0.0 ; extra == 'voc'
